webvtt/__init__.py
webvtt/cli.py
webvtt/errors.py
webvtt/models.py
webvtt/parsers.py
webvtt/sbv.py
webvtt/segmenter.py
webvtt/srt.py
webvtt/structures.py
webvtt/utils.py
webvtt/vtt.py
webvtt/webvtt.py
webvtt/writers.py
webvtt_py-0.5.1.dist-info/LICENSE
webvtt_py-0.5.1.dist-info/METADATA
webvtt_py-0.5.1.dist-info/WHEEL
webvtt_py-0.5.1.dist-info/entry_points.txt
webvtt_py-0.5.1.dist-info/top_level.txt
webvtt_py-0.5.1.dist-info/RECORD
